{
    "Contrat Social": [
        {
            "type": "Nominal",
            "intertextual_function": 1,
            "semantic": "Neutral"
        },
        {
            "type": "Nominal",
            "intertextual_function": 1,
            "semantic": "Neutral"
        }
    ],
    "Declaration of August": [
        {
            "type": "Thematic",
            "intertextual_function": 3,
            "semantic": "Neutral"
        }
    ],
    "Rousseau": [
        {
            "type": "Nominal",
            "intertextual_function": [
                "3"
            ],
            "semantic": "Negative"
        },
        {
            "type": "Nominal",
            "intertextual_function": 1,
            "semantic": "Positive"
        }
    ],
    "Declaration of Rights": [
        {
            "type": "Thematic",
            "intertextual_function": [
                "2"
            ],
            "semantic": "Positive"
        }
    ],
    "_Contrat Social_": [
        {
            "type": "Nominal",
            "intertextual_function": [
                "3"
            ],
            "semantic": "Negative"
        }
    ],
    "Taine": [
        {
            "type": "Thematic",
            "intertextual_function": [
                "3"
            ],
            "semantic": "Positive"
        }
    ],
    "Janet": [
        {
            "type": "Nominal",
            "intertextual_function": [
                "3"
            ],
            "semantic": "Negative"
        }
    ],
    "Paul Janet": [
        {
            "type": "Nominal",
            "intertextual_function": 1,
            "semantic": "Positive"
        }
    ],
    "Unidentified": [
        {
            "type": "Nominal",
            "intertextual_function": 1,
            "semantic": "Neutral"
        }
    ]
}