{
    "M. Taine": [
        {
            "type": "Nominal",
            "intertextual_function": 1,
            "semantic": "Negative"
        },
        {
            "type": "Nominal",
            "intertextual_function": [
                "3"
            ],
            "semantic": "Positive"
        },
        {
            "type": "Nominal",
            "intertextual_function": 1,
            "semantic": "Negative"
        },
        {
            "type": "Nominal",
            "intertextual_function": [
                "3"
            ],
            "semantic": "Negative"
        },
        {
            "type": "Nominal",
            "intertextual_function": [
                "3"
            ],
            "semantic": "Negative"
        }
    ],
    "Les origines de la France contemporaine": [
        {
            "type": "Verbal",
            "intertextual_function": 2,
            "semantic": "Neutral"
        }
    ],
    "Charles Krauthammer": [
        {
            "type": "Nominal",
            "intertextual_function": 1,
            "semantic": "Neutral"
        }
    ],
    "John Stuart Mill": [
        {
            "type": "Verbal",
            "intertextual_function": 2,
            "semantic": "Neutral"
        }
    ],
    "Nassau W.": [
        {
            "type": "Thematic",
            "intertextual_function": 3,
            "semantic": "Neutral"
        }
    ],
    "Aristotle": [
        {
            "type": "Nominal",
            "intertextual_function": 1,
            "semantic": "Neutral"
        }
    ],
    "Boxhorn": [
        {
            "type": "Verbal",
            "intertextual_function": 2,
            "semantic": "Neutral"
        }
    ],
    "F. Engels": [
        {
            "type": "Thematic",
            "intertextual_function": 3,
            "semantic": "Neutral"
        }
    ],
    "French Revolution": [
        {
            "type": "Thematic",
            "intertextual_function": [
                "1"
            ],
            "semantic": "Neutral"
        }
    ],
    "M. Royer-Collard": [
        {
            "type": "Verbal",
            "intertextual_function": 2,
            "semantic": "Neutral"
        }
    ],
    "Mérimée": [
        {
            "type": "Verbal",
            "intertextual_function": [
                "3"
            ],
            "semantic": "Neutral"
        }
    ],
    "Phlogiston": [
        {
            "type": "Thematic",
            "intertextual_function": 3,
            "semantic": "Negative"
        }
    ],
    "Caracalla": [
        {
            "type": "Thematic",
            "intertextual_function": 3,
            "semantic": "Neutral"
        }
    ],
    "Unidentified": [
        {
            "type": "Thematic",
            "intertextual_function": 3,
            "semantic": "Neutral"
        },
        {
            "type": "Nominal",
            "intertextual_function": 1,
            "semantic": "Neutral"
        },
        {
            "type": "Nominal",
            "intertextual_function": 1,
            "semantic": "Neutral"
        },
        {
            "type": "Nominal",
            "intertextual_function": 1,
            "semantic": "Neutral"
        }
    ],
    "M. Zola": [
        {
            "type": "Nominal",
            "intertextual_function": [
                "3"
            ],
            "semantic": "Neutral"
        }
    ],
    "Kant": [
        {
            "type": "Nominal",
            "intertextual_function": [
                "2"
            ],
            "semantic": "Neutral"
        }
    ],
    "Professor Giddings": [
        {
            "type": "Thematic",
            "intertextual_function": [
                "4"
            ],
            "semantic": "Positive"
        }
    ],
    "Shaftesbury": [
        {
            "type": "Nominal",
            "intertextual_function": [
                "4"
            ],
            "semantic": "Positive"
        }
    ],
    "Eus•be\nSalverte": [
        {
            "type": "Verbal",
            "intertextual_function": 2,
            "semantic": "Neutral"
        }
    ],
    "*Professor Giddings—Adam Smith": [
        {
            "type": "Thematic",
            "intertextual_function": 3,
            "semantic": "Neutral"
        }
    ],
    "Comte": [
        {
            "type": "Thematic",
            "intertextual_function": [
                "3"
            ],
            "semantic": "Negative"
        }
    ],
    "Buckle": [
        {
            "type": "Nominal",
            "intertextual_function": [
                "3"
            ],
            "semantic": "Negative"
        }
    ],
    "A learned and judicious English": [
        {
            "type": "Thematic",
            "intertextual_function": 3,
            "semantic": "Neutral"
        }
    ]
}