{
    "Sir William Petty": [
        {
            "type": "Nominal",
            "intertextual_function": 1,
            "semantic": "Neutral"
        }
    ],
    "Ulster massacre of": [
        {
            "type": "Nominal",
            "intertextual_function": 1,
            "semantic": "Neutral"
        }
    ],
    "Romans": [
        {
            "type": "Nominal",
            "intertextual_function": 1,
            "semantic": "Neutral"
        }
    ],
    "Christianising Germans in the Dark Ages": [
        {
            "type": "Nominal",
            "intertextual_function": 1,
            "semantic": "Neutral"
        }
    ],
    "Dr. Gardiner": [
        {
            "type": "Nominal",
            "intertextual_function": [
                "3"
            ],
            "semantic": "Negative"
        },
        {
            "type": "Nominal",
            "intertextual_function": [
                "3"
            ],
            "semantic": "Negative"
        },
        {
            "type": "Verbal",
            "intertextual_function": 2,
            "semantic": "Positive"
        },
        {
            "type": "Thematic",
            "intertextual_function": [
                "3"
            ],
            "semantic": "Positive"
        }
    ],
    "Mr. Harrison": [
        {
            "type": "Verbal",
            "intertextual_function": [
                "3"
            ],
            "semantic": "Neutral"
        },
        {
            "type": "Nominal",
            "intertextual_function": [
                "3"
            ],
            "semantic": "Neutral"
        },
        {
            "type": "Verbal",
            "intertextual_function": 2,
            "semantic": "Neutral"
        }
    ],
    "Royalist Manley": [
        {
            "type": "Thematic",
            "intertextual_function": [
                "3"
            ],
            "semantic": "Neutral"
        }
    ],
    "Dr.": [
        {
            "type": "Nominal",
            "intertextual_function": 1,
            "semantic": "Neutral"
        }
    ],
    "Dr. Gardiner—Commonwealth and Protectorate": [
        {
            "type": "Verbal",
            "intertextual_function": 2,
            "semantic": "Negative"
        }
    ],
    "Catholicism": [
        {
            "type": "Thematic",
            "intertextual_function": 3,
            "semantic": "Neutral"
        }
    ],
    "Anglicanism": [
        {
            "type": "Thematic",
            "intertextual_function": 3,
            "semantic": "Neutral"
        }
    ],
    "Calvinism": [
        {
            "type": "Thematic",
            "intertextual_function": 3,
            "semantic": "Neutral"
        }
    ],
    "Lutheranism": [
        {
            "type": "Thematic",
            "intertextual_function": 3,
            "semantic": "Neutral"
        }
    ],
    "Calvin": [
        {
            "type": "Thematic",
            "intertextual_function": [
                "2"
            ],
            "semantic": "Neutral"
        }
    ],
    "Elizabeth": [
        {
            "type": "Thematic",
            "intertextual_function": [
                "1"
            ],
            "semantic": "Neutral"
        },
        {
            "type": "Nominal",
            "intertextual_function": [
                "2"
            ],
            "semantic": "Neutral"
        }
    ],
    "Cromwell": [
        {
            "type": "Thematic",
            "intertextual_function": [
                "2"
            ],
            "semantic": "Neutral"
        },
        {
            "type": "Nominal",
            "intertextual_function": [
                "3"
            ],
            "semantic": "Negative"
        },
        {
            "type": "Thematic",
            "intertextual_function": 3,
            "semantic": "Neutral"
        },
        {
            "type": "Nominal",
            "intertextual_function": 1,
            "semantic": "Negative"
        },
        {
            "type": "Nominal",
            "intertextual_function": 1,
            "semantic": "Neutral"
        },
        {
            "type": "Thematic",
            "intertextual_function": [
                "1"
            ],
            "semantic": "Neutral"
        },
        {
            "type": "Verbal",
            "intertextual_function": 2,
            "semantic": "Neutral"
        },
        {
            "type": "Verbal",
            "intertextual_function": 2,
            "semantic": "Negative"
        },
        {
            "type": "Nominal",
            "intertextual_function": [
                "2"
            ],
            "semantic": "Negative"
        },
        {
            "type": "Thematic",
            "intertextual_function": 3,
            "semantic": "Neutral"
        },
        {
            "type": "Nominal",
            "intertextual_function": 1,
            "semantic": "Neutral"
        }
    ],
    "Dutch": [
        {
            "type": "Thematic",
            "intertextual_function": [
                "2"
            ],
            "semantic": "Neutral"
        }
    ],
    "Puritanism": [
        {
            "type": "Thematic",
            "intertextual_function": [
                "3"
            ],
            "semantic": "Negative"
        }
    ],
    "Elizabethan Poor Law": [
        {
            "type": "Thematic",
            "intertextual_function": [
                "2"
            ],
            "semantic": "Neutral"
        }
    ],
    "Arnold": [
        {
            "type": "Nominal",
            "intertextual_function": [
                "3"
            ],
            "semantic": "Neutral"
        }
    ],
    "Frederic Harrison": [
        {
            "type": "Nominal",
            "intertextual_function": [
                "3"
            ],
            "semantic": "Negative"
        }
    ],
    "Louis XIV": [
        {
            "type": "Nominal",
            "intertextual_function": [
                "1"
            ],
            "semantic": "Neutral"
        }
    ],
    "Philip II": [
        {
            "type": "Nominal",
            "intertextual_function": [
                "1"
            ],
            "semantic": "Neutral"
        }
    ],
    "Napoleon": [
        {
            "type": "Nominal",
            "intertextual_function": [
                "1"
            ],
            "semantic": "Neutral"
        },
        {
            "type": "Thematic",
            "intertextual_function": [
                "2"
            ],
            "semantic": "Neutral"
        }
    ],
    "Charles": [
        {
            "type": "Nominal",
            "intertextual_function": [
                "3"
            ],
            "semantic": "Neutral"
        },
        {
            "type": "Verbal",
            "intertextual_function": 2,
            "semantic": "Neutral"
        },
        {
            "type": "Nominal",
            "intertextual_function": 1,
            "semantic": "Neutral"
        },
        {
            "type": "Thematic",
            "intertextual_function": 3,
            "semantic": "Neutral"
        }
    ],
    "Hampden": [
        {
            "type": "Nominal",
            "intertextual_function": [
                "2"
            ],
            "semantic": "Neutral"
        },
        {
            "type": "Nominal",
            "intertextual_function": [
                "2"
            ],
            "semantic": "Neutral"
        }
    ],
    "Ludlow": [
        {
            "type": "Nominal",
            "intertextual_function": [
                "3"
            ],
            "semantic": "Neutral"
        },
        {
            "type": "Nominal",
            "intertextual_function": [
                "2"
            ],
            "semantic": "Neutral"
        }
    ],
    "Hallam": [
        {
            "type": "Nominal",
            "intertextual_function": [
                "3"
            ],
            "semantic": "Neutral"
        },
        {
            "type": "Thematic",
            "intertextual_function": [
                "2"
            ],
            "semantic": "Neutral"
        },
        {
            "type": "Nominal",
            "intertextual_function": [
                "2"
            ],
            "semantic": "Neutral"
        },
        {
            "type": "Nominal",
            "intertextual_function": 1,
            "semantic": "Neutral"
        },
        {
            "type": "Nominal",
            "intertextual_function": [
                "2"
            ],
            "semantic": "Neutral"
        }
    ],
    "Vaughan": [
        {
            "type": "Nominal",
            "intertextual_function": [
                "3"
            ],
            "semantic": "Neutral"
        },
        {
            "type": "Verbal",
            "intertextual_function": [
                "2"
            ],
            "semantic": "Positive"
        },
        {
            "type": "Nominal",
            "intertextual_function": [
                "2"
            ],
            "semantic": "Neutral"
        }
    ],
    "Milton": [
        {
            "type": "Nominal",
            "intertextual_function": [
                "3"
            ],
            "semantic": "Neutral"
        },
        {
            "type": "Nominal",
            "intertextual_function": [
                "2"
            ],
            "semantic": "Negative"
        }
    ],
    "Protestantism": [
        {
            "type": "Nominal",
            "intertextual_function": [
                "1"
            ],
            "semantic": "Neutral"
        }
    ],
    "Catholic": [
        {
            "type": "Nominal",
            "intertextual_function": [
                "1"
            ],
            "semantic": "Neutral"
        },
        {
            "type": "Nominal",
            "intertextual_function": [
                "2"
            ],
            "semantic": "Neutral"
        }
    ],
    "Independents": [
        {
            "type": "Nominal",
            "intertextual_function": 1,
            "semantic": "Neutral"
        }
    ],
    "Lilburne": [
        {
            "type": "Verbal",
            "intertextual_function": 2,
            "semantic": "Neutral"
        }
    ],
    "Presbyterians": [
        {
            "type": "Nominal",
            "intertextual_function": 1,
            "semantic": "Neutral"
        },
        {
            "type": "Nominal",
            "intertextual_function": [
                "2"
            ],
            "semantic": "Neutral"
        }
    ],
    "Episcopalians": [
        {
            "type": "Verbal",
            "intertextual_function": 2,
            "semantic": "Neutral"
        },
        {
            "type": "Nominal",
            "intertextual_function": [
                "2"
            ],
            "semantic": "Neutral"
        }
    ],
    "Oliver Cromwell": [
        {
            "type": "Nominal",
            "intertextual_function": [
                "2"
            ],
            "semantic": "Negative"
        }
    ],
    "Gardiner": [
        {
            "type": "Nominal",
            "intertextual_function": [
                "3"
            ],
            "semantic": "Neutral"
        },
        {
            "type": "Verbal",
            "intertextual_function": 2,
            "semantic": "Positive"
        },
        {
            "type": "Nominal",
            "intertextual_function": 1,
            "semantic": "Neutral"
        },
        {
            "type": "Nominal",
            "intertextual_function": [
                "2"
            ],
            "semantic": "Neutral"
        }
    ],
    "Com. and Prot.": [
        {
            "type": "Thematic",
            "intertextual_function": [
                "1"
            ],
            "semantic": "Neutral"
        }
    ],
    "History of the Commonwealth": [
        {
            "type": "Thematic",
            "intertextual_function": 3,
            "semantic": "Neutral"
        }
    ],
    "Anthony ? Wood": [
        {
            "type": "Thematic",
            "intertextual_function": 3,
            "semantic": "Neutral"
        }
    ],
    "Anthony's Autobiography": [
        {
            "type": "Thematic",
            "intertextual_function": [
                "2"
            ],
            "semantic": "Neutral"
        }
    ],
    "Cromwellian": [
        {
            "type": "Thematic",
            "intertextual_function": [
                "2"
            ],
            "semantic": "Negative"
        }
    ],
    "Parliamentary": [
        {
            "type": "Thematic",
            "intertextual_function": [
                "1"
            ],
            "semantic": "Negative"
        }
    ],
    "Puritan": [
        {
            "type": "Nominal",
            "intertextual_function": [
                "1"
            ],
            "semantic": "Negative"
        },
        {
            "type": "Thematic",
            "intertextual_function": 3,
            "semantic": "Neutral"
        },
        {
            "type": "Nominal",
            "intertextual_function": 1,
            "semantic": "Neutral"
        },
        {
            "type": "Verbal",
            "intertextual_function": [
                "1"
            ],
            "semantic": "Negative"
        }
    ],
    "Cavaliers": [
        {
            "type": "Nominal",
            "intertextual_function": [
                "1"
            ],
            "semantic": "Neutral"
        }
    ],
    "Catholics": [
        {
            "type": "Nominal",
            "intertextual_function": [
                "1"
            ],
            "semantic": "Neutral"
        }
    ],
    "Independent priests": [
        {
            "type": "Nominal",
            "intertextual_function": [
                "1"
            ],
            "semantic": "Neutral"
        }
    ],
    "the Bible": [
        {
            "type": "Nominal",
            "intertextual_function": 1,
            "semantic": "Neutral"
        }
    ],
    "the Lord": [
        {
            "type": "Verbal",
            "intertextual_function": 2,
            "semantic": "Neutral"
        }
    ],
    "Dr. Gardiner—_History of the Commonwealth_": [
        {
            "type": "Nominal",
            "intertextual_function": [
                "3"
            ],
            "semantic": "Neutral"
        }
    ],
    "Father French—_Narrative of the Earl of Clarendon's Settlement and Sale of Ireland_": [
        {
            "type": "Thematic",
            "intertextual_function": 3,
            "semantic": "Neutral"
        }
    ],
    "Unidentified": [
        {
            "type": "Thematic",
            "intertextual_function": 3,
            "semantic": "Neutral"
        }
    ],
    "Dr. Cunningham": [
        {
            "type": "Nominal",
            "intertextual_function": [
                "3"
            ],
            "semantic": "Negative"
        }
    ],
    "Mosheim": [
        {
            "type": "Thematic",
            "intertextual_function": [
                "1"
            ],
            "semantic": "Neutral"
        }
    ],
    "Seneca": [
        {
            "type": "Nominal",
            "intertextual_function": [
                "1"
            ],
            "semantic": "Neutral"
        }
    ],
    "Paul": [
        {
            "type": "Thematic",
            "intertextual_function": [
                "1"
            ],
            "semantic": "Neutral"
        }
    ],
    "Torquemada": [
        {
            "type": "Nominal",
            "intertextual_function": 1,
            "semantic": "Neutral"
        }
    ],
    "Alva": [
        {
            "type": "Verbal",
            "intertextual_function": 2,
            "semantic": "Neutral"
        }
    ],
    "Carlyle": [
        {
            "type": "Nominal",
            "intertextual_function": 1,
            "semantic": "Negative"
        },
        {
            "type": "Verbal",
            "intertextual_function": 2,
            "semantic": "Positive"
        },
        {
            "type": "Nominal",
            "intertextual_function": [
                "2"
            ],
            "semantic": "Neutral"
        },
        {
            "type": "Thematic",
            "intertextual_function": [
                "2"
            ],
            "semantic": "Negative"
        }
    ],
    "Villemain": [
        {
            "type": "Nominal",
            "intertextual_function": 1,
            "semantic": "Negative"
        }
    ],
    "Cromwell (implied through the context of his": [
        {
            "type": "Thematic",
            "intertextual_function": 3,
            "semantic": "Neutral"
        }
    ],
    "Buckingham": [
        {
            "type": "Nominal",
            "intertextual_function": [
                "2"
            ],
            "semantic": "Neutral"
        }
    ],
    "Puritans": [
        {
            "type": "Nominal",
            "intertextual_function": [
                "2"
            ],
            "semantic": "Neutral"
        }
    ],
    "Protestant": [
        {
            "type": "Nominal",
            "intertextual_function": [
                "2"
            ],
            "semantic": "Neutral"
        }
    ],
    "Arminians": [
        {
            "type": "Nominal",
            "intertextual_function": [
                "2"
            ],
            "semantic": "Neutral"
        },
        {
            "type": "Nominal",
            "intertextual_function": 1,
            "semantic": "Negative"
        }
    ],
    "Marian period": [
        {
            "type": "Nominal",
            "intertextual_function": [
                "2"
            ],
            "semantic": "Neutral"
        }
    ],
    "Alva (massacres of": [
        {
            "type": "Nominal",
            "intertextual_function": 1,
            "semantic": "Neutral"
        }
    ],
    "St. Bartholomew's Day": [
        {
            "type": "Nominal",
            "intertextual_function": 1,
            "semantic": "Neutral"
        }
    ],
    "James (James": [
        {
            "type": "Nominal",
            "intertextual_function": 1,
            "semantic": "Neutral"
        }
    ],
    "Spanish marriage": [
        {
            "type": "Nominal",
            "intertextual_function": [
                "2"
            ],
            "semantic": "Neutral"
        }
    ],
    "King of France (daughter of": [
        {
            "type": "Nominal",
            "intertextual_function": 1,
            "semantic": "Neutral"
        }
    ],
    "Tudors": [
        {
            "type": "Nominal",
            "intertextual_function": 1,
            "semantic": "Neutral"
        }
    ],
    "Privy Council": [
        {
            "type": "Nominal",
            "intertextual_function": 1,
            "semantic": "Neutral"
        }
    ],
    "Parliamentarians": [
        {
            "type": "Nominal",
            "intertextual_function": 1,
            "semantic": "Neutral"
        }
    ],
    "Eliot": [
        {
            "type": "Nominal",
            "intertextual_function": 1,
            "semantic": "Neutral"
        },
        {
            "type": "Thematic",
            "intertextual_function": 3,
            "semantic": "Negative"
        }
    ],
    "Laud": [
        {
            "type": "Nominal",
            "intertextual_function": 1,
            "semantic": "Neutral"
        }
    ],
    "Star Chamber": [
        {
            "type": "Nominal",
            "intertextual_function": 1,
            "semantic": "Neutral"
        }
    ],
    "Papists": [
        {
            "type": "Thematic",
            "intertextual_function": 3,
            "semantic": "Neutral"
        }
    ],
    "Corporation of London": [
        {
            "type": "Nominal",
            "intertextual_function": 1,
            "semantic": "Neutral"
        }
    ],
    "Vandyke": [
        {
            "type": "Nominal",
            "intertextual_function": [
                "2"
            ],
            "semantic": "Neutral"
        }
    ],
    "Independency": [
        {
            "type": "Nominal",
            "intertextual_function": [
                "1"
            ],
            "semantic": "Neutral"
        }
    ],
    "James I": [
        {
            "type": "Nominal",
            "intertextual_function": 1,
            "semantic": "Neutral"
        },
        {
            "type": "Thematic",
            "intertextual_function": [
                "2"
            ],
            "semantic": "Neutral"
        }
    ],
    "Pym": [
        {
            "type": "Verbal",
            "intertextual_function": 2,
            "semantic": "Neutral"
        },
        {
            "type": "Thematic",
            "intertextual_function": [
                "2"
            ],
            "semantic": "Neutral"
        }
    ],
    "Popery": [
        {
            "type": "Nominal",
            "intertextual_function": 1,
            "semantic": "Neutral"
        }
    ],
    "Cowley": [
        {
            "type": "Nominal",
            "intertextual_function": [
                "2"
            ],
            "semantic": "Neutral"
        }
    ],
    "Prof. Firth": [
        {
            "type": "Thematic",
            "intertextual_function": [
                "2"
            ],
            "semantic": "Neutral"
        }
    ],
    "Charles II": [
        {
            "type": "Thematic",
            "intertextual_function": [
                "2"
            ],
            "semantic": "Neutral"
        }
    ],
    "Lomas": [
        {
            "type": "Nominal",
            "intertextual_function": [
                "2"
            ],
            "semantic": "Neutral"
        }
    ],
    "Prendergast": [
        {
            "type": "Nominal",
            "intertextual_function": [
                "2"
            ],
            "semantic": "Neutral"
        }
    ],
    "Cunningham": [
        {
            "type": "Nominal",
            "intertextual_function": [
                "2"
            ],
            "semantic": "Neutral"
        }
    ],
    "Episcopalian": [
        {
            "type": "Thematic",
            "intertextual_function": [
                "2"
            ],
            "semantic": "Neutral"
        }
    ],
    "Nonconformist": [
        {
            "type": "Thematic",
            "intertextual_function": [
                "2"
            ],
            "semantic": "Neutral"
        }
    ],
    "Commonwealth": [
        {
            "type": "Thematic",
            "intertextual_function": [
                "2"
            ],
            "semantic": "Neutral"
        }
    ],
    "Republican": [
        {
            "type": "Thematic",
            "intertextual_function": [
                "2"
            ],
            "semantic": "Neutral"
        }
    ],
    "Great Rebellion": [
        {
            "type": "Thematic",
            "intertextual_function": [
                "2"
            ],
            "semantic": "Neutral"
        }
    ],
    "Protectorate": [
        {
            "type": "Thematic",
            "intertextual_function": [
                "2"
            ],
            "semantic": "Neutral"
        }
    ],
    "American colonies": [
        {
            "type": "Thematic",
            "intertextual_function": 3,
            "semantic": "Neutral"
        }
    ],
    "George III": [
        {
            "type": "Thematic",
            "intertextual_function": 3,
            "semantic": "Neutral"
        }
    ],
    "Parliament of Richard Cromwell": [
        {
            "type": "Thematic",
            "intertextual_function": 3,
            "semantic": "Neutral"
        }
    ],
    "French Revolution": [
        {
            "type": "Thematic",
            "intertextual_function": 3,
            "semantic": "Neutral"
        }
    ],
    "divine right": [
        {
            "type": "Thematic",
            "intertextual_function": [
                "2"
            ],
            "semantic": "Neutral"
        }
    ],
    "Falkland": [
        {
            "type": "Nominal",
            "intertextual_function": [
                "3"
            ],
            "semantic": "Neutral"
        }
    ],
    "Macaulay": [
        {
            "type": "Thematic",
            "intertextual_function": [
                "3"
            ],
            "semantic": "Neutral"
        }
    ],
    "Waller": [
        {
            "type": "Nominal",
            "intertextual_function": 1,
            "semantic": "Neutral"
        },
        {
            "type": "Nominal",
            "intertextual_function": 1,
            "semantic": "Neutral"
        }
    ],
    "Marvell": [
        {
            "type": "Thematic",
            "intertextual_function": 3,
            "semantic": "Neutral"
        },
        {
            "type": "Nominal",
            "intertextual_function": 1,
            "semantic": "Neutral"
        }
    ],
    "Mohammed": [
        {
            "type": "Nominal",
            "intertextual_function": [
                "2"
            ],
            "semantic": "Neutral"
        }
    ],
    "D'Aubigné": [
        {
            "type": "Nominal",
            "intertextual_function": 1,
            "semantic": "Neutral"
        }
    ],
    "The Bible": [
        {
            "type": "Thematic",
            "intertextual_function": 3,
            "semantic": "Positive"
        }
    ],
    "Christian pietism": [
        {
            "type": "Nominal",
            "intertextual_function": [
                "3"
            ],
            "semantic": "Negative"
        }
    ],
    "_Areopagitica_": [
        {
            "type": "Nominal",
            "intertextual_function": [
                "2"
            ],
            "semantic": "Positive"
        }
    ],
    "_Eikonoklastes_": [
        {
            "type": "Nominal",
            "intertextual_function": [
                "2"
            ],
            "semantic": "Negative"
        }
    ],
    "Hobbes": [
        {
            "type": "Nominal",
            "intertextual_function": 1,
            "semantic": "Positive"
        }
    ],
    "Christianity": [
        {
            "type": "Thematic",
            "intertextual_function": 3,
            "semantic": "Neutral"
        }
    ],
    "Judaism": [
        {
            "type": "Thematic",
            "intertextual_function": 3,
            "semantic": "Neutral"
        }
    ],
    "Pentateuch": [
        {
            "type": "Thematic",
            "intertextual_function": 3,
            "semantic": "Neutral"
        }
    ],
    "Hebrew sacred books": [
        {
            "type": "Nominal",
            "intertextual_function": 1,
            "semantic": "Neutral"
        }
    ],
    "Carlylean": [
        {
            "type": "Thematic",
            "intertextual_function": 3,
            "semantic": "Neutral"
        }
    ],
    "Clarendon": [
        {
            "type": "Nominal",
            "intertextual_function": [
                "3"
            ],
            "semantic": "Negative"
        }
    ],
    "Whitelocke": [
        {
            "type": "Nominal",
            "intertextual_function": [
                "2"
            ],
            "semantic": "Neutral"
        }
    ],
    "Admiral Blake": [
        {
            "type": "Nominal",
            "intertextual_function": 1,
            "semantic": "Neutral"
        }
    ],
    "Van Tromp": [
        {
            "type": "Thematic",
            "intertextual_function": 3,
            "semantic": "Neutral"
        }
    ],
    "Stayner": [
        {
            "type": "Thematic",
            "intertextual_function": 3,
            "semantic": "Neutral"
        }
    ]
}